neofs_testlib/__init__.py
neofs_testlib/defaults.py
neofs_testlib/blockchain/__init__.py
neofs_testlib/blockchain/multisig.py
neofs_testlib/blockchain/role_designation.py
neofs_testlib/blockchain/rpc_client.py
neofs_testlib/cli/__init__.py
neofs_testlib/cli/cli_command.py
neofs_testlib/cli/neofs_adm/__init__.py
neofs_testlib/cli/neofs_adm/adm.py
neofs_testlib/cli/neofs_adm/config.py
neofs_testlib/cli/neofs_adm/morph.py
neofs_testlib/cli/neofs_adm/storage_config.py
neofs_testlib/cli/neofs_adm/subnet.py
neofs_testlib/cli/neofs_adm/version.py
neofs_testlib/cli/neofs_authmate/__init__.py
neofs_testlib/cli/neofs_authmate/authmate.py
neofs_testlib/cli/neofs_authmate/secret.py
neofs_testlib/cli/neofs_authmate/version.py
neofs_testlib/cli/neofs_cli/__init__.py
neofs_testlib/cli/neofs_cli/accounting.py
neofs_testlib/cli/neofs_cli/acl.py
neofs_testlib/cli/neofs_cli/bearer.py
neofs_testlib/cli/neofs_cli/cli.py
neofs_testlib/cli/neofs_cli/container.py
neofs_testlib/cli/neofs_cli/control.py
neofs_testlib/cli/neofs_cli/netmap.py
neofs_testlib/cli/neofs_cli/object.py
neofs_testlib/cli/neofs_cli/session.py
neofs_testlib/cli/neofs_cli/shards.py
neofs_testlib/cli/neofs_cli/storagegroup.py
neofs_testlib/cli/neofs_cli/util.py
neofs_testlib/cli/neofs_cli/version.py
neofs_testlib/cli/neogo/__init__.py
neofs_testlib/cli/neogo/candidate.py
neofs_testlib/cli/neogo/contract.py
neofs_testlib/cli/neogo/db.py
neofs_testlib/cli/neogo/go.py
neofs_testlib/cli/neogo/nep17.py
neofs_testlib/cli/neogo/network_type.py
neofs_testlib/cli/neogo/node.py
neofs_testlib/cli/neogo/query.py
neofs_testlib/cli/neogo/version.py
neofs_testlib/cli/neogo/wallet.py
neofs_testlib/env/__init__.py
neofs_testlib/env/env.py
neofs_testlib/env/templates/cli_cfg.yaml
neofs_testlib/env/templates/http.yaml
neofs_testlib/env/templates/ir.yaml
neofs_testlib/env/templates/neofs_env_config.yaml
neofs_testlib/env/templates/network.yaml
neofs_testlib/env/templates/rest.yaml
neofs_testlib/env/templates/s3.yaml
neofs_testlib-1.1.26.dist-info/LICENSE
neofs_testlib-1.1.26.dist-info/METADATA
neofs_testlib-1.1.26.dist-info/WHEEL
neofs_testlib-1.1.26.dist-info/entry_points.txt
neofs_testlib-1.1.26.dist-info/top_level.txt
neofs_testlib-1.1.26.dist-info/RECORD
